<properties>

    <property id="BackgroundColor" type="number">0x000000</property>
    <property id="ForegroundColor" type="number">0xFFFFFF</property>
    <property id="Font" type="number">3</property>
    
    <property id="WhatToShowAtTop" type="number">1</property>
	<property id="WhatToShowAtRight" type="number">1</property>
    <property id="ShowBottomLeft" type="boolean">true</property>
    <property id="WhatToShowAtBottomLeft" type="number">1</property>
	<property id="WhatToShowAtBottomLeft2" type="number">3</property>
	<property id="WhatToShowAtBottomLeft3" type="number">4</property>
	
	<property id="UseOldFont" type="boolean">false</property>
	
	<property id="BTCOnnection" type="number">0</property>
	

</properties>
